{"index.md":"5896489b","karte-action-sdk.afterupdate.md":"d69fc6ed","karte-action-sdk.applycss.md":"9566677e","karte-action-sdk.actionprops.data.md":"78af0895","karte-action-sdk.applyglobalcss.md":"8874b4cf","karte-action-sdk.actionprops.md":"1c0fac0f","karte-action-sdk.closeaction.md":"b476b223","karte-action-sdk.beforeupdate.md":"d19e7e73","karte-action-sdk.actionclosehook.md":"d6ca8622","karte-action-sdk.actionhook.md":"d68741bc","karte-action-sdk.actioneventhandler.md":"66a631c5","karte-action-sdk.actionoptions.localvariablesquery.md":"f8f52dd8","karte-action-sdk.actionoptions.md":"8451c4e2","karte-action-sdk.actionoptions.props.md":"d87f53c2","karte-action-sdk.actionoptions.oncreate.md":"6cc76281","karte-action-sdk.addfreeanswer.md":"02002b0b","karte-action-sdk.actionchangestatehook.md":"28b8400f","karte-action-sdk.actionoptions.publish.md":"00d8c4ac","karte-action-sdk.actionoptions.send.md":"e16c1d38","karte-action-sdk.widget.actionvariables.md":"0948a1e9","karte-action-sdk.widget.actionprops.send.md":"3c3e9964","karte-action-sdk.widget.actiontablequeryparam.md":"131e58d6","karte-action-sdk.widget.applycss.md":"84da2859","karte-action-sdk.widget.actiontableresult.md":"eabcd3f4","karte-action-sdk.onscrollcontext.previousrate.md":"998c2aff","karte-action-sdk.onscroll.md":"20797d63","karte-action-sdk.loadglobalstyle.md":"09f8e725","karte-action-sdk.scrolldirection.md":"a6da1341","karte-action-sdk.widget.actiontablequeryparams.md":"264648ec","karte-action-sdk.actionprops.onshow.md":"fe931c28","karte-action-sdk.widget.getmemorystore.md":"cb3cb9ca","karte-action-sdk.actionoptions.kartetemplate.md":"e81fa2e6","karte-action-sdk.ontime.md":"f50e8a32","karte-action-sdk.widget.method.md":"d3583a2a","karte-action-sdk.closetrigger.md":"68f867be","karte-action-sdk.systemconfig.md":"4e732e1e","karte-action-sdk.widget.collection.md":"a5a5922a","karte-action-sdk.onscrollcontext.direction.md":"22855402","karte-action-sdk.widget.sendfunction.md":"55bffa6e","karte-action-sdk.widget.setlocalstore.md":"0ecb8ab1","karte-action-sdk.widget.setstate.md":"4792afad","karte-action-sdk.addchoiceanswer.md":"98865f68","karte-action-sdk.actionprops.onchangestate.md":"e7fdb2c3","karte-action-sdk.loadstyle.md":"00eb0aa2","karte-action-sdk.actionoptions.context.md":"d78c134f","karte-action-sdk.collection.md":"25ce2a21","karte-action-sdk.onchangestate.md":"1634ecd9","karte-action-sdk.loadglobalscript.md":"035acb78","karte-action-sdk.destroyaction.md":"eacf2e95","karte-action-sdk.md":"06db6890","karte-action-sdk.onclose.md":"395e5357","karte-action-sdk.getansweredquestion.md":"369c6234","karte-action-sdk.widget.actionprops.publish.md":"4766ea45","karte-action-sdk.resetvariables.md":"04e24084","karte-action-sdk.widget.actionoptions.localvariablesquery.md":"7979aa04","karte-action-sdk.onscrollfunction.md":"019ab6e3","karte-action-sdk.onscrollcontext.deltarate.md":"c2ab1302","karte-action-sdk.isopened.md":"1d4cc54f","karte-action-sdk.widget.actioneventhandler.md":"8f97ea20","karte-action-sdk.oncreate.md":"a901969b","karte-action-sdk.onmount.md":"ee290699","karte-action-sdk.ondestroy.md":"0d89049c","karte-action-sdk.tick.md":"7bf245c1","karte-action-sdk.reseteventhandlers.md":"8a2c2161","karte-action-sdk.setvariables.md":"fac05bc1","karte-action-sdk.showaction.md":"0c22443a","karte-action-sdk.collectionconfig.md":"6adc3ec0","karte-action-sdk.widget.actionprops.onshow.md":"95c062c5","karte-action-sdk.onscrollcontext.md":"aac86406","karte-action-sdk.widget.changevalcallback.md":"fa428e9e","karte-action-sdk.widget.closeaction.md":"231ebcdb","karte-action-sdk.widget.closetrigger.md":"15f3275a","karte-action-sdk.font.md":"d7ca6613","karte-action-sdk.widget.actionhook.md":"41b0947a","karte-action-sdk.widget.collectionconfig.md":"95f2c81f","karte-action-sdk.ondestory.md":"dfc58218","karte-action-sdk.widget.actionoptions.send.md":"199792cd","karte-action-sdk.widget.collection_0.md":"069a26f4","karte-action-sdk.publishfunction.md":"62c4680b","karte-action-sdk.widget.loadstyle.md":"914e3a3f","karte-action-sdk.widget.modalprops.md":"8b105848","karte-action-sdk.widget.md":"4e5137c3","karte-action-sdk.sendanswer.md":"7660f4b6","karte-action-sdk.layout_component_names.md":"4f7e62e8","karte-action-sdk.widget.onchangestate.md":"c8cd8919","karte-action-sdk.widget.on.md":"92fd1d83","karte-action-sdk.widget.onchangeval.md":"44575677","karte-action-sdk.widget.onclose.md":"e144769a","karte-action-sdk.onscrollcontext.rate.md":"cd1a9a5a","karte-action-sdk.widget.publishfunction.md":"4d5e9aa6","karte-action-sdk.widget.onshow.md":"7e030edb","karte-action-sdk.sendfunction.md":"faf7222c","karte-action-sdk.sendanswers.md":"56b4f9f0","karte-action-sdk.widget.setmemorystore.md":"de02e209","karte-action-sdk.setsetting.md":"54b57dc3","karte-action-sdk.seteventhandlers.md":"e841157b","karte-action-sdk.widget.showaction.md":"04dfb42e","karte-action-sdk.widget.setval.md":"3f66a136","karte-action-sdk.widget.widgeteventname.md":"f33999cb","karte-action-sdk.widget.systemconfig.md":"a80760b2","karte-action-sdk.widget.actionoptions.publish.md":"c7595101","karte-action-sdk.widget.storage.md":"06ca4a47","karte-action-sdk.widget.actionoptions.kartetemplate.md":"07cb4157","karte-action-sdk.widget.actionoptions.variables.md":"4027cb00","karte-action-sdk.getcssvariables.md":"c126c187","karte-action-sdk.widget.actionrunnercontext.md":"d4f69ab8","karte-action-sdk.widget.actionsetting.md":"5f5f7ca3","karte-action-sdk.getstate.md":"a88fc550","karte-action-sdk.formidentifytextfields.md":"07f223da","karte-action-sdk.getactionroot.md":"711be868","karte-action-sdk.setstate.md":"f922a9c9","karte-action-sdk.onscrollcontext.scrollrate.md":"c27a22af","karte-action-sdk.widget.actionprops.data.md":"702e454b","karte-action-sdk.getstates.md":"74d7d93c","karte-action-sdk.getvariables.md":"af7e7f70","karte-action-sdk.create.md":"31901e76","karte-action-sdk.widget.actionprops.onchangestate.md":"8864ac95","karte-action-sdk.widget.actionoptions.oncreate.md":"2e6c330f","karte-action-sdk.widget.actionoptions.context.md":"ab115b15","karte-action-sdk.actionvariables.md":"e9b409e6","karte-action-sdk.geteventhandlers.md":"bfd6091b","karte-action-sdk.actionoptions.variables.md":"bee031d9","karte-action-sdk.widget.actionprops.md":"7fb4fab4","karte-action-sdk.widget.actionoptions.props.md":"3d2d41d8","karte-action-sdk.widget.actionclosehook.md":"68486be3","karte-action-sdk.widget.getstate.md":"1e79a98b","karte-action-sdk.widget.getval.md":"ce8e1439","karte-action-sdk.widget.eventcallback.md":"76c8f05a","karte-action-sdk.getansweredquestionids.md":"4ebbfff5","karte-action-sdk.getsystem.md":"d4580e7d","karte-action-sdk.actionprops.publish.md":"b5477986","karte-action-sdk.onshow.md":"da4e5600","karte-action-sdk.removeanswer.md":"dd844e8b","karte-action-sdk.widget.getcssvariables.md":"09d90af8","karte-action-sdk.widget.getlocalstore.md":"5f166711","karte-action-sdk.widget.actionchangestatehook.md":"e0f00162","karte-action-sdk.widget.getactionroot.md":"37b90f8c","karte-action-sdk.actionprops.send.md":"14d8a24a","karte-action-sdk.widget.actionoptions.md":"03d026ce"}
